arcbeam_langchain_connector/.ruff_cache/.gitignore
arcbeam_langchain_connector/.ruff_cache/CACHEDIR.TAG
arcbeam_langchain_connector/__init__.py
arcbeam_langchain_connector/langchain_utils.py
arcbeam_langchain_connector-0.0.5rc1.dist-info/WHEEL
arcbeam_langchain_connector-0.0.5rc1.dist-info/entry_points.txt
arcbeam_langchain_connector-0.0.5rc1.dist-info/METADATA
arcbeam_langchain_connector-0.0.5rc1.dist-info/RECORD
