Metadata-Version: 2.3
Name: arcbeam-langchain-connector
Version: 0.0.5rc1
Summary: Add your description here
Author: Arcbeam Eng
Author-email: Arcbeam Eng <eng@arcbeam.ai>
Requires-Dist: langchain>=0.3.27
Requires-Python: >=3.13
